mnistvit/__init__.py
mnistvit/__main__.py
mnistvit/model.py
mnistvit/predict.py
mnistvit/preprocess.py
mnistvit/train.py
mnistvit/tune.py
mnistvit/utils.py
mnistvit-1.4.2.dist-info/licenses/LICENSE
mnistvit-1.4.2.dist-info/METADATA
mnistvit-1.4.2.dist-info/WHEEL
mnistvit-1.4.2.dist-info/top_level.txt
mnistvit-1.4.2.dist-info/RECORD
