Metadata-Version: 2.4
Name: mnistvit
Version: 1.4.2
Summary: A vision transformer for training on MNIST
Author-email: Arno Onken <asnelt@asnelt.org>
License-Expression: GPL-3.0-only
Project-URL: Homepage, https://github.com/asnelt/mnistvit/
Project-URL: Bug Tracker, https://github.com/asnelt/mnistvit/issues/
Keywords: mnist,pytorch,transformer,vision,vit
Classifier: Development Status :: 5 - Production/Stable
Classifier: Intended Audience :: Science/Research
Classifier: Operating System :: OS Independent
Classifier: Programming Language :: Python :: 3
Classifier: Topic :: Scientific/Engineering :: Artificial Intelligence
Requires-Python: >=3.10
License-File: LICENSE
Requires-Dist: torch>=2.6
Requires-Dist: torchvision>=0.21
Provides-Extra: tune
Requires-Dist: ray[tune]>=2.50; extra == "tune"
Requires-Dist: optuna>=4.5; extra == "tune"
Dynamic: license-file
